libsettings.pypy37-pp73-x86_64-linux-gnu.so
libsettings-0.1.14.dist-info/METADATA
libsettings-0.1.14.dist-info/LICENSE
libsettings-0.1.14.dist-info/top_level.txt
libsettings-0.1.14.dist-info/RECORD
libsettings-0.1.14.dist-info/WHEEL
